ezpy_logs/LoggerFactory.py
ezpy_logs/__init__.py
ezpy_logs/delete_old_logs.py
ezpy_logs/disable_external_loggers.py
ezpy_logs-0.1.2.dist-info/METADATA
ezpy_logs-0.1.2.dist-info/WHEEL
ezpy_logs-0.1.2.dist-info/RECORD
